search/__init__.py
search/__main__.py
search/choices.py
search/decorator.py
search/models.toml
search/viewer.py
chatgpt_search-0.0.5.dist-info/METADATA
chatgpt_search-0.0.5.dist-info/WHEEL
chatgpt_search-0.0.5.dist-info/entry_points.txt
chatgpt_search-0.0.5.dist-info/top_level.txt
chatgpt_search-0.0.5.dist-info/RECORD
