Metadata-Version: 2.1
Name: chatgpt-search
Version: 0.0.5
Summary: package for search with chatgpt in cli
Author-email: Abhijeet Kumar <krabhijeet93@gmail.com>
Project-URL: Homepage, https://github.com/abhijeetkr93/chatgpt-search
Keywords: search
Classifier: License :: OSI Approved :: MIT License
Classifier: Programming Language :: Python
Classifier: Programming Language :: Python :: 3
Requires-Python: >=3.8
Requires-Dist: openai
Requires-Dist: html2text
Requires-Dist: sgmllib3k
Requires-Dist: tomli
Provides-Extra: dev
Requires-Dist: black ; extra == 'dev'
Requires-Dist: bumpver ; extra == 'dev'
Requires-Dist: isort ; extra == 'dev'
Requires-Dist: pip-tools ; extra == 'dev'
Requires-Dist: pytest ; extra == 'dev'
